{
  "ID": 112730,
  "UUID": "E0D1684A-09C6-4C91-B18D-98EEBEFF7D61",
  "ParentChargePointID": null,
  "DataProviderID": 1,
  "DataProvidersReference": null,
  "OperatorID": 3330,
  "OperatorsReference": null,
  "UsageTypeID": 0,
  "UsageCost": null,
  "AddressInfo": {
    "ID": 113076,
    "Title": " Montedoro Shopping Center | Repower",
    "AddressLine1": "Via Flavia di Stramare, 119",
    "AddressLine2": null,
    "Town": "Muggia",
    "StateOrProvince": "TS",
    "Postcode": "34015 ",
    "CountryID": 112,
    "Country": {
      "ID": 112,
      "Title": "Italy",
      "ISOCode": "IT",
      "ContinentCode": "EU"
    },
    "Latitude": 45.5944652276569,
    "Longitude": 13.8067659332373,
    "ContactTelephone1": "+39 040 232320",
    "ContactTelephone2": null,
    "ContactEmail": "info@montedoroshoppingcenter.it",
    "AccessComments": null,
    "RelatedURL": "http://www.montedoroshoppingcenter.it",
    "Distance": null,
    "DistanceUnit": 0,
    "GeneralComments": null
  },
  "Connections": [
    {
      "ID": 158731,
      "ConnectionTypeID": 25,
      "ConnectionType": {
        "ID": 25,
        "Title": "Type 2 (Socket Only)",
        "FormalName": "IEC 62196-2 Type 2",
        "IsDiscontinued": false,
        "IsObsolete": false
      },
      "Reference": null,
      "StatusTypeID": 50,
      "StatusType": {
        "ID": 50,
        "Title": "Operational",
        "IsOperational": true,
        "IsUserSelectable": true
      },
      "LevelID": 2,
      "Level": {
        "ID": 2,
        "Title": "Level 2 : Medium (Over 2kW)",
        "Comments": "Over 2 kW, usually non-domestic socket type",
        "IsFastChargeCapable": false
      },
      "Amps": null,
      "Voltage": null,
      "PowerKW": null,
      "CurrentTypeID": null,
      "CurrentType": null,
      "Quantity": 2,
      "Comments": null
    },
    {
      "ID": 158732,
      "ConnectionTypeID": 36,
      "ConnectionType": {
        "ID": 36,
        "Title": "SCAME Type 3A (Low Power)",
        "FormalName": null,
        "IsDiscontinued": false,
        "IsObsolete": false
      },
      "Reference": null,
      "StatusTypeID": 50,
      "StatusType": {
        "ID": 50,
        "Title": "Operational",
        "IsOperational": true,
        "IsUserSelectable": true
      },
      "LevelID": 2,
      "Level": {
        "ID": 2,
        "Title": "Level 2 : Medium (Over 2kW)",
        "Comments": "Over 2 kW, usually non-domestic socket type",
        "IsFastChargeCapable": false
      },
      "Amps": 16,
      "Voltage": 240,
      "PowerKW": 3.7,
      "CurrentTypeID": 10,
      "CurrentType": {
        "ID": 10,
        "Title": "AC (Single-Phase)",
        "Description": "Alternating Current - Single Phase"
      },
      "Quantity": 2,
      "Comments": null
    }
  ],
  "NumberOfPoints": 4,
  "GeneralComments": null,
  "DatePlanned": null,
  "DateLastConfirmed": null,
  "StatusTypeID": 50,
  "DateLastStatusUpdate": {
    "$date": "2019-01-13T17:40:00Z"
  },
  "MetadataValues": null,
  "DataQualityLevel": 1,
  "DateCreated": {
    "$date": "2018-11-13T08:56:00Z"
  },
  "SubmissionStatusTypeID": 200,
  "AddressCleaningRequired": false,
  "DataProvider": {
    "ID": 1,
    "Title": "Open Charge Map Contributors",
    "WebsiteURL": "http://openchargemap.org",
    "Comments": null,
    "DataProviderStatusType": {
      "ID": 1,
      "Title": "Manual Data Entry",
      "IsProviderEnabled": true
    },
    "IsRestrictedEdit": false,
    "IsOpenDataLicensed": true,
    "IsApprovedImport": true,
    "License": "Licensed under Creative Commons Attribution-ShareAlike 4.0 International (CC BY-SA 4.0)",
    "DateLastImported": null
  },
  "OperatorInfo": {
    "ID": 3330,
    "Title": "Repower (Italy)",
    "WebsiteURL": "https://www.repower.com/it/la-mobilita-elettrica/",
    "Comments": null,
    "PhonePrimaryContact": null,
    "PhoneSecondaryContact": null,
    "IsPrivateIndividual": false,
    "AddressInfo": null,
    "BookingURL": null,
    "ContactEmail": null,
    "FaultReportEmail": null,
    "IsRestrictedEdit": false
  },
  "UsageType": {
    "ID": 0,
    "Title": "(Unknown)",
    "IsPayAtLocation": null,
    "IsMembershipRequired": null,
    "IsAccessKeyRequired": null
  },
  "StatusType": {
    "ID": 50,
    "Title": "Operational",
    "IsOperational": true,
    "IsUserSelectable": true
  },
  "SubmissionStatus": {
    "ID": 200,
    "Title": "Submission Published",
    "IsLive": true
  },
  "UserComments": null,
  "PercentageSimilarity": null,
  "MediaItems": null,
  "LevelOfDetail": null,
  "Chargers": null,
  "MetadataTags": null,
  "SpatialPosition": {
    "type": "Point",
    "coordinates": [
      13.8067659332373,
      45.5944652276569
    ]
  }
}
