{
  "ID": 157499,
  "UUID": "3B82703A-5C39-420C-BE23-EA8531DB947F",
  "ParentChargePointID": null,
  "DataProviderID": 1,
  "DataProvidersReference": null,
  "OperatorID": 3382,
  "OperatorsReference": null,
  "UsageTypeID": 4,
  "UsageCost": null,
  "AddressInfo": {
    "ID": 157853,
    "Title": "Dalmine Piscine FAST | RESSOLAR",
    "AddressLine1": "Via Monte Tofane",
    "AddressLine2": null,
    "Town": "Dalmine",
    "StateOrProvince": "BG",
    "Postcode": "24044",
    "CountryID": 112,
    "Country": {
      "ID": 112,
      "Title": "Italy",
      "ISOCode": "IT",
      "ContinentCode": "EU"
    },
    "Latitude": 45.64352171465862,
    "Longitude": 9.613142820744201,
    "ContactTelephone1": "+39 035 36 92 145",
    "ContactTelephone2": null,
    "ContactEmail": "info@ressolar.it",
    "AccessComments": null,
    "RelatedURL": "https://www.ressolar.it/mobilita-sostenibile/",
    "Distance": null,
    "DistanceUnit": 0,
    "GeneralComments": null
  },
  "Connections": [
    {
      "ID": 226879,
      "ConnectionTypeID": 33,
      "ConnectionType": {
        "ID": 33,
        "Title": "CCS (Type 2)",
        "FormalName": "IEC 62196-3 Configuration FF",
        "IsDiscontinued": false,
        "IsObsolete": false
      },
      "Reference": null,
      "StatusTypeID": 50,
      "StatusType": {
        "ID": 50,
        "Title": "Operational",
        "IsOperational": true,
        "IsUserSelectable": true
      },
      "LevelID": 3,
      "Level": {
        "ID": 3,
        "Title": "Level 3:  High (Over 40kW)",
        "Comments": "40KW and Higher",
        "IsFastChargeCapable": true
      },
      "Amps": 120,
      "Voltage": 400,
      "PowerKW": 50,
      "CurrentTypeID": 30,
      "CurrentType": {
        "ID": 30,
        "Title": "DC",
        "Description": "Direct Current"
      },
      "Quantity": 1,
      "Comments": null
    },
    {
      "ID": 226880,
      "ConnectionTypeID": 2,
      "ConnectionType": {
        "ID": 2,
        "Title": "CHAdeMO",
        "FormalName": "IEC 62196-3 Configuration AA",
        "IsDiscontinued": null,
        "IsObsolete": null
      },
      "Reference": null,
      "StatusTypeID": 50,
      "StatusType": {
        "ID": 50,
        "Title": "Operational",
        "IsOperational": true,
        "IsUserSelectable": true
      },
      "LevelID": 3,
      "Level": {
        "ID": 3,
        "Title": "Level 3:  High (Over 40kW)",
        "Comments": "40KW and Higher",
        "IsFastChargeCapable": true
      },
      "Amps": 120,
      "Voltage": 400,
      "PowerKW": 50,
      "CurrentTypeID": 30,
      "CurrentType": {
        "ID": 30,
        "Title": "DC",
        "Description": "Direct Current"
      },
      "Quantity": 1,
      "Comments": null
    },
    {
      "ID": 226881,
      "ConnectionTypeID": 25,
      "ConnectionType": {
        "ID": 25,
        "Title": "Type 2 (Socket Only)",
        "FormalName": "IEC 62196-2 Type 2",
        "IsDiscontinued": false,
        "IsObsolete": false
      },
      "Reference": null,
      "StatusTypeID": 50,
      "StatusType": {
        "ID": 50,
        "Title": "Operational",
        "IsOperational": true,
        "IsUserSelectable": true
      },
      "LevelID": 2,
      "Level": {
        "ID": 2,
        "Title": "Level 2 : Medium (Over 2kW)",
        "Comments": "Over 2 kW, usually non-domestic socket type",
        "IsFastChargeCapable": false
      },
      "Amps": 32,
      "Voltage": 400,
      "PowerKW": 22,
      "CurrentTypeID": 20,
      "CurrentType": {
        "ID": 20,
        "Title": "AC (Three-Phase)",
        "Description": "Alternating Current - Three Phase"
      },
      "Quantity": 1,
      "Comments": null
    }
  ],
  "NumberOfPoints": 2,
  "GeneralComments": "Si attiva si attiva con l'app Wroom",
  "DatePlanned": null,
  "DateLastConfirmed": null,
  "StatusTypeID": 50,
  "DateLastStatusUpdate": {
    "$date": "2020-07-11T17:11:00Z"
  },
  "MetadataValues": null,
  "DataQualityLevel": 1,
  "DateCreated": {
    "$date": "2020-06-11T06:48:00Z"
  },
  "SubmissionStatusTypeID": 200,
  "AddressCleaningRequired": false,
  "DataProvider": {
    "ID": 1,
    "Title": "Open Charge Map Contributors",
    "WebsiteURL": "http://openchargemap.org",
    "Comments": null,
    "DataProviderStatusType": {
      "ID": 1,
      "Title": "Manual Data Entry",
      "IsProviderEnabled": true
    },
    "IsRestrictedEdit": false,
    "IsOpenDataLicensed": true,
    "IsApprovedImport": true,
    "License": "Licensed under Creative Commons Attribution-ShareAlike 4.0 International (CC BY-SA 4.0)",
    "DateLastImported": null
  },
  "OperatorInfo": {
    "ID": 3382,
    "Title": "Wroom",
    "WebsiteURL": "https://wroom.org/",
    "Comments": "App based access",
    "PhonePrimaryContact": "+39 035 36 92 145",
    "PhoneSecondaryContact": null,
    "IsPrivateIndividual": false,
    "AddressInfo": null,
    "BookingURL": null,
    "ContactEmail": null,
    "FaultReportEmail": null,
    "IsRestrictedEdit": false
  },
  "UsageType": {
    "ID": 4,
    "Title": "Public - Membership Required",
    "IsPayAtLocation": false,
    "IsMembershipRequired": true,
    "IsAccessKeyRequired": true
  },
  "StatusType": {
    "ID": 50,
    "Title": "Operational",
    "IsOperational": true,
    "IsUserSelectable": true
  },
  "SubmissionStatus": {
    "ID": 200,
    "Title": "Submission Published",
    "IsLive": true
  },
  "UserComments": [
    {
      "ID": 22895,
      "ChargePointID": 157499,
      "CommentTypeID": 10,
      "CommentType": {
        "ID": 10,
        "Title": "General Comment"
      },
      "UserName": "polianto",
      "Comment": "Zona impianti sportivi, numerosi bar e ristoranti raggiungibili a piedi nei dintorni https://www.forumelettrico.it/forum/colonnina-ressolar-fast-impianti-sportivi-di-dalmine-via-tofane-t11396.html",
      "Rating": 4,
      "RelatedURL": "https://www.forumelettrico.it/forum/colonnina-ressolar-fast-impianti-sportivi-di-dalmine-via-tofane-t11396.html",
      "DateCreated": {
        "$date": "2020-07-11T17:11:16.627Z"
      },
      "User": {
        "ID": 1606,
        "IdentityProvider": null,
        "Identifier": null,
        "CurrentSessionToken": null,
        "Username": "polianto",
        "Profile": null,
        "Location": null,
        "WebsiteURL": null,
        "ReputationPoints": 12396,
        "Permissions": null,
        "PermissionsRequested": null,
        "DateCreated": null,
        "DateLastLogin": null,
        "IsProfilePublic": null,
        "IsEmergencyChargingProvider": null,
        "IsPublicChargingProvider": null,
        "Latitude": null,
        "Longitude": null,
        "EmailAddress": null,
        "EmailHash": null,
        "ProfileImageURL": "https://www.gravatar.com/avatar/173761d62438ae07e57afd55e258f3a5?s=80&d=robohash",
        "IsCurrentSessionTokenValid": null,
        "APIKey": null,
        "SyncedSettings": null
      },
      "CheckinStatusTypeID": 10,
      "CheckinStatusType": {
        "ID": 10,
        "Title": "Charged Successfully",
        "IsPositive": true,
        "IsAutomatedCheckin": false
      },
      "IsActionedByEditor": false
    }
  ],
  "PercentageSimilarity": null,
  "MediaItems": [
    {
      "ID": 23020,
      "ChargePointID": 157499,
      "ItemURL": "https://s3-ap-southeast-2.amazonaws.com/openchargemap/images/IT/OCM157499/OCM-157499.orig.2020071116473291.jpg",
      "ItemThumbnailURL": "https://s3-ap-southeast-2.amazonaws.com/openchargemap/images/IT/OCM157499/OCM-157499.thmb.2020071116473291.jpg",
      "Comment": "",
      "IsEnabled": true,
      "IsVideo": false,
      "IsFeaturedItem": false,
      "IsExternalResource": false,
      "MetadataValue": null,
      "User": {
        "ID": 1606,
        "IdentityProvider": null,
        "Identifier": null,
        "CurrentSessionToken": null,
        "Username": "polianto",
        "Profile": null,
        "Location": null,
        "WebsiteURL": null,
        "ReputationPoints": 12396,
        "Permissions": null,
        "PermissionsRequested": null,
        "DateCreated": null,
        "DateLastLogin": null,
        "IsProfilePublic": null,
        "IsEmergencyChargingProvider": null,
        "IsPublicChargingProvider": null,
        "Latitude": null,
        "Longitude": null,
        "EmailAddress": null,
        "EmailHash": null,
        "ProfileImageURL": "https://www.gravatar.com/avatar/173761d62438ae07e57afd55e258f3a5?s=80&d=robohash",
        "IsCurrentSessionTokenValid": null,
        "APIKey": null,
        "SyncedSettings": null
      },
      "DateCreated": {
        "$date": "2020-07-11T16:48:00Z"
      }
    },
    {
      "ID": 23018,
      "ChargePointID": 157499,
      "ItemURL": "https://s3-ap-southeast-2.amazonaws.com/openchargemap/images/IT/OCM157499/OCM-157499.orig.2020071116465998.jpg",
      "ItemThumbnailURL": "https://s3-ap-southeast-2.amazonaws.com/openchargemap/images/IT/OCM157499/OCM-157499.thmb.2020071116465998.jpg",
      "Comment": "",
      "IsEnabled": true,
      "IsVideo": false,
      "IsFeaturedItem": false,
      "IsExternalResource": false,
      "MetadataValue": null,
      "User": {
        "ID": 1606,
        "IdentityProvider": null,
        "Identifier": null,
        "CurrentSessionToken": null,
        "Username": "polianto",
        "Profile": null,
        "Location": null,
        "WebsiteURL": null,
        "ReputationPoints": 12396,
        "Permissions": null,
        "PermissionsRequested": null,
        "DateCreated": null,
        "DateLastLogin": null,
        "IsProfilePublic": null,
        "IsEmergencyChargingProvider": null,
        "IsPublicChargingProvider": null,
        "Latitude": null,
        "Longitude": null,
        "EmailAddress": null,
        "EmailHash": null,
        "ProfileImageURL": "https://www.gravatar.com/avatar/173761d62438ae07e57afd55e258f3a5?s=80&d=robohash",
        "IsCurrentSessionTokenValid": null,
        "APIKey": null,
        "SyncedSettings": null
      },
      "DateCreated": {
        "$date": "2020-07-11T16:47:00Z"
      }
    },
    {
      "ID": 23019,
      "ChargePointID": 157499,
      "ItemURL": "https://s3-ap-southeast-2.amazonaws.com/openchargemap/images/IT/OCM157499/OCM-157499.orig.2020071116471384.jpg",
      "ItemThumbnailURL": "https://s3-ap-southeast-2.amazonaws.com/openchargemap/images/IT/OCM157499/OCM-157499.thmb.2020071116471384.jpg",
      "Comment": "",
      "IsEnabled": true,
      "IsVideo": false,
      "IsFeaturedItem": false,
      "IsExternalResource": false,
      "MetadataValue": null,
      "User": {
        "ID": 1606,
        "IdentityProvider": null,
        "Identifier": null,
        "CurrentSessionToken": null,
        "Username": "polianto",
        "Profile": null,
        "Location": null,
        "WebsiteURL": null,
        "ReputationPoints": 12396,
        "Permissions": null,
        "PermissionsRequested": null,
        "DateCreated": null,
        "DateLastLogin": null,
        "IsProfilePublic": null,
        "IsEmergencyChargingProvider": null,
        "IsPublicChargingProvider": null,
        "Latitude": null,
        "Longitude": null,
        "EmailAddress": null,
        "EmailHash": null,
        "ProfileImageURL": "https://www.gravatar.com/avatar/173761d62438ae07e57afd55e258f3a5?s=80&d=robohash",
        "IsCurrentSessionTokenValid": null,
        "APIKey": null,
        "SyncedSettings": null
      },
      "DateCreated": {
        "$date": "2020-07-11T16:47:00Z"
      }
    }
  ],
  "LevelOfDetail": null,
  "Chargers": null,
  "MetadataTags": null,
  "SpatialPosition": {
    "type": "Point",
    "coordinates": [
      9.613142820744201,
      45.64352171465862
    ]
  }
}
