{
  "ID": 19639,
  "UUID": "6F9EA743-2DBC-43FF-8E72-B0EE09926943",
  "ParentChargePointID": null,
  "DataProviderID": 1,
  "DataProvidersReference": null,
  "OperatorID": 19,
  "OperatorsReference": null,
  "UsageTypeID": 1,
  "UsageCost": null,
  "AddressInfo": {
    "ID": 19984,
    "Title": "Best Western Parkmore Hotel & Leisure Club",
    "AddressLine1": "636 Yarm Rd",
    "AddressLine2": "Stockton-on-Tees",
    "Town": null,
    "StateOrProvince": null,
    "Postcode": "TS16 0DH",
    "CountryID": 1,
    "Country": {
      "ID": 1,
      "Title": "United Kingdom",
      "ISOCode": "GB",
      "ContinentCode": "EU"
    },
    "Latitude": 54.5218458,
    "Longitude": -1.3506531,
    "ContactTelephone1": "0845 373 0780",
    "ContactTelephone2": null,
    "ContactEmail": null,
    "AccessComments": null,
    "RelatedURL": "http://www.parkmorehotel.co.uk/",
    "Distance": null,
    "DistanceUnit": 0,
    "GeneralComments": null
  },
  "Connections": [
    {
      "ID": 19867,
      "ConnectionTypeID": 25,
      "ConnectionType": {
        "ID": 25,
        "Title": "Type 2 (Socket Only)",
        "FormalName": "IEC 62196-2 Type 2",
        "IsDiscontinued": false,
        "IsObsolete": false
      },
      "Reference": null,
      "StatusTypeID": 50,
      "StatusType": {
        "ID": 50,
        "Title": "Operational",
        "IsOperational": true,
        "IsUserSelectable": true
      },
      "LevelID": 2,
      "Level": {
        "ID": 2,
        "Title": "Level 2 : Medium (Over 2kW)",
        "Comments": "Over 2 kW, usually non-domestic socket type",
        "IsFastChargeCapable": false
      },
      "Amps": 32,
      "Voltage": 230,
      "PowerKW": 7,
      "CurrentTypeID": 10,
      "CurrentType": {
        "ID": 10,
        "Title": "AC (Single-Phase)",
        "Description": "Alternating Current - Single Phase"
      },
      "Quantity": 1,
      "Comments": null
    },
    {
      "ID": 19868,
      "ConnectionTypeID": 3,
      "ConnectionType": {
        "ID": 3,
        "Title": "BS1363 3 Pin 13 Amp",
        "FormalName": "BS1363 / Type G",
        "IsDiscontinued": null,
        "IsObsolete": null
      },
      "Reference": null,
      "StatusTypeID": 50,
      "StatusType": {
        "ID": 50,
        "Title": "Operational",
        "IsOperational": true,
        "IsUserSelectable": true
      },
      "LevelID": 2,
      "Level": {
        "ID": 2,
        "Title": "Level 2 : Medium (Over 2kW)",
        "Comments": "Over 2 kW, usually non-domestic socket type",
        "IsFastChargeCapable": false
      },
      "Amps": 13,
      "Voltage": 230,
      "PowerKW": 3,
      "CurrentTypeID": 10,
      "CurrentType": {
        "ID": 10,
        "Title": "AC (Single-Phase)",
        "Description": "Alternating Current - Single Phase"
      },
      "Quantity": 1,
      "Comments": null
    }
  ],
  "NumberOfPoints": 2,
  "GeneralComments": null,
  "DatePlanned": null,
  "DateLastConfirmed": null,
  "StatusTypeID": 50,
  "DateLastStatusUpdate": {
    "$date": "2019-05-02T16:42:00Z"
  },
  "MetadataValues": [
    {
      "ID": 224,
      "MetadataFieldID": 4,
      "ItemValue": "Data © OpenStreetMap contributors, ODbL 1.0. http://www.openstreetmap.org/copyright",
      "MetadataFieldOption": null,
      "MetadataFieldOptionID": null
    }
  ],
  "DataQualityLevel": 1,
  "DateCreated": {
    "$date": "2013-10-09T08:29:00Z"
  },
  "SubmissionStatusTypeID": 200,
  "AddressCleaningRequired": false,
  "DataProvider": {
    "ID": 1,
    "Title": "Open Charge Map Contributors",
    "WebsiteURL": "http://openchargemap.org",
    "Comments": null,
    "DataProviderStatusType": {
      "ID": 1,
      "Title": "Manual Data Entry",
      "IsProviderEnabled": true
    },
    "IsRestrictedEdit": false,
    "IsOpenDataLicensed": true,
    "IsApprovedImport": true,
    "License": "Licensed under Creative Commons Attribution-ShareAlike 4.0 International (CC BY-SA 4.0)",
    "DateLastImported": null
  },
  "OperatorInfo": {
    "ID": 19,
    "Title": "Zero Carbon World",
    "WebsiteURL": "http://zerocarbonworld.org/",
    "Comments": "UK Charity promoting carbon reduction",
    "PhonePrimaryContact": null,
    "PhoneSecondaryContact": null,
    "IsPrivateIndividual": false,
    "AddressInfo": null,
    "BookingURL": null,
    "ContactEmail": "info@zerocarbonworld.com",
    "FaultReportEmail": "info@zerocarbonworld.com",
    "IsRestrictedEdit": null
  },
  "UsageType": {
    "ID": 1,
    "Title": "Public",
    "IsPayAtLocation": null,
    "IsMembershipRequired": null,
    "IsAccessKeyRequired": null
  },
  "StatusType": {
    "ID": 50,
    "Title": "Operational",
    "IsOperational": true,
    "IsUserSelectable": true
  },
  "SubmissionStatus": {
    "ID": 200,
    "Title": "Submission Published",
    "IsLive": true
  },
  "UserComments": null,
  "PercentageSimilarity": null,
  "MediaItems": [
    {
      "ID": 18231,
      "ChargePointID": 19639,
      "ItemURL": "https://s3-ap-southeast-2.amazonaws.com/openchargemap/images/GB/OCM19639/OCM-19639.orig.2019050216415202.jpg",
      "ItemThumbnailURL": "https://s3-ap-southeast-2.amazonaws.com/openchargemap/images/GB/OCM19639/OCM-19639.thmb.2019050216415202.jpg",
      "Comment": "",
      "IsEnabled": true,
      "IsVideo": false,
      "IsFeaturedItem": false,
      "IsExternalResource": false,
      "MetadataValue": null,
      "User": {
        "ID": 15366,
        "IdentityProvider": null,
        "Identifier": null,
        "CurrentSessionToken": null,
        "Username": "ZCWCara",
        "Profile": null,
        "Location": null,
        "WebsiteURL": null,
        "ReputationPoints": 522,
        "Permissions": null,
        "PermissionsRequested": null,
        "DateCreated": null,
        "DateLastLogin": null,
        "IsProfilePublic": null,
        "IsEmergencyChargingProvider": null,
        "IsPublicChargingProvider": null,
        "Latitude": null,
        "Longitude": null,
        "EmailAddress": null,
        "EmailHash": null,
        "ProfileImageURL": "https://www.gravatar.com/avatar/7461f0dcedb3750bdc1cc7a5fae75362?s=80&d=robohash",
        "IsCurrentSessionTokenValid": null,
        "APIKey": null,
        "SyncedSettings": null
      },
      "DateCreated": {
        "$date": "2019-05-02T16:42:00Z"
      }
    }
  ],
  "LevelOfDetail": null,
  "Chargers": null,
  "MetadataTags": null,
  "SpatialPosition": {
    "type": "Point",
    "coordinates": [
      -1.3506531,
      54.5218458
    ]
  }
}
