{
  "ID": 20922,
  "UUID": "BEE1DB9C-06AD-4A9E-84FB-06DFEE613AB1",
  "ParentChargePointID": null,
  "DataProviderID": 1,
  "DataProvidersReference": null,
  "OperatorID": 19,
  "OperatorsReference": null,
  "UsageTypeID": 1,
  "UsageCost": null,
  "AddressInfo": {
    "ID": 21267,
    "Title": "Pentillie Castle",
    "AddressLine1": "Paynters Cross",
    "AddressLine2": "St. Mellion",
    "Town": "Saltash",
    "StateOrProvince": "Cornwall",
    "Postcode": "PL12 6QD",
    "CountryID": 1,
    "Country": {
      "ID": 1,
      "Title": "United Kingdom",
      "ISOCode": "GB",
      "ContinentCode": "EU"
    },
    "Latitude": 50.46006,
    "Longitude": -4.242142,
    "ContactTelephone1": "01579 350 044",
    "ContactTelephone2": null,
    "ContactEmail": "contact@pentillie.co.uk",
    "AccessComments": null,
    "RelatedURL": "http://www.pentillie.co.uk/",
    "Distance": null,
    "DistanceUnit": 0,
    "GeneralComments": null
  },
  "Connections": [
    {
      "ID": 22789,
      "ConnectionTypeID": 1,
      "ConnectionType": {
        "ID": 1,
        "Title": "Type 1 (J1772)",
        "FormalName": "SAE J1772-2009",
        "IsDiscontinued": null,
        "IsObsolete": null
      },
      "Reference": null,
      "StatusTypeID": 50,
      "StatusType": {
        "ID": 50,
        "Title": "Operational",
        "IsOperational": true,
        "IsUserSelectable": true
      },
      "LevelID": 2,
      "Level": {
        "ID": 2,
        "Title": "Level 2 : Medium (Over 2kW)",
        "Comments": "Over 2 kW, usually non-domestic socket type",
        "IsFastChargeCapable": false
      },
      "Amps": 13,
      "Voltage": 230,
      "PowerKW": 3.7,
      "CurrentTypeID": 10,
      "CurrentType": {
        "ID": 10,
        "Title": "AC (Single-Phase)",
        "Description": "Alternating Current - Single Phase"
      },
      "Quantity": 1,
      "Comments": null
    },
    {
      "ID": 177013,
      "ConnectionTypeID": 30,
      "ConnectionType": {
        "ID": 30,
        "Title": "Tesla (Model S/X)",
        "FormalName": null,
        "IsDiscontinued": false,
        "IsObsolete": false
      },
      "Reference": null,
      "StatusTypeID": 50,
      "StatusType": {
        "ID": 50,
        "Title": "Operational",
        "IsOperational": true,
        "IsUserSelectable": true
      },
      "LevelID": 2,
      "Level": {
        "ID": 2,
        "Title": "Level 2 : Medium (Over 2kW)",
        "Comments": "Over 2 kW, usually non-domestic socket type",
        "IsFastChargeCapable": false
      },
      "Amps": 32,
      "Voltage": 230,
      "PowerKW": 7,
      "CurrentTypeID": 10,
      "CurrentType": {
        "ID": 10,
        "Title": "AC (Single-Phase)",
        "Description": "Alternating Current - Single Phase"
      },
      "Quantity": 1,
      "Comments": null
    }
  ],
  "NumberOfPoints": 2,
  "GeneralComments": "3rd Party ZeroNet addition (Podpoint CS, Tesla)",
  "DatePlanned": null,
  "DateLastConfirmed": null,
  "StatusTypeID": 50,
  "DateLastStatusUpdate": {
    "$date": "2019-05-15T15:42:00Z"
  },
  "MetadataValues": null,
  "DataQualityLevel": 1,
  "DateCreated": {
    "$date": "2014-01-28T11:32:00Z"
  },
  "SubmissionStatusTypeID": 200,
  "AddressCleaningRequired": false,
  "DataProvider": {
    "ID": 1,
    "Title": "Open Charge Map Contributors",
    "WebsiteURL": "http://openchargemap.org",
    "Comments": null,
    "DataProviderStatusType": {
      "ID": 1,
      "Title": "Manual Data Entry",
      "IsProviderEnabled": true
    },
    "IsRestrictedEdit": false,
    "IsOpenDataLicensed": true,
    "IsApprovedImport": true,
    "License": "Licensed under Creative Commons Attribution-ShareAlike 4.0 International (CC BY-SA 4.0)",
    "DateLastImported": null
  },
  "OperatorInfo": {
    "ID": 19,
    "Title": "Zero Carbon World",
    "WebsiteURL": "http://zerocarbonworld.org/",
    "Comments": "UK Charity promoting carbon reduction",
    "PhonePrimaryContact": null,
    "PhoneSecondaryContact": null,
    "IsPrivateIndividual": false,
    "AddressInfo": null,
    "BookingURL": null,
    "ContactEmail": "info@zerocarbonworld.com",
    "FaultReportEmail": "info@zerocarbonworld.com",
    "IsRestrictedEdit": null
  },
  "UsageType": {
    "ID": 1,
    "Title": "Public",
    "IsPayAtLocation": null,
    "IsMembershipRequired": null,
    "IsAccessKeyRequired": null
  },
  "StatusType": {
    "ID": 50,
    "Title": "Operational",
    "IsOperational": true,
    "IsUserSelectable": true
  },
  "SubmissionStatus": {
    "ID": 200,
    "Title": "Submission Published",
    "IsLive": true
  },
  "UserComments": null,
  "PercentageSimilarity": null,
  "MediaItems": [
    {
      "ID": 18391,
      "ChargePointID": 20922,
      "ItemURL": "https://s3-ap-southeast-2.amazonaws.com/openchargemap/images/GB/OCM20922/OCM-20922.orig.2019051510574211.jpg",
      "ItemThumbnailURL": "https://s3-ap-southeast-2.amazonaws.com/openchargemap/images/GB/OCM20922/OCM-20922.thmb.2019051510574211.jpg",
      "Comment": "",
      "IsEnabled": true,
      "IsVideo": false,
      "IsFeaturedItem": false,
      "IsExternalResource": false,
      "MetadataValue": null,
      "User": {
        "ID": 15366,
        "IdentityProvider": null,
        "Identifier": null,
        "CurrentSessionToken": null,
        "Username": "ZCWCara",
        "Profile": null,
        "Location": null,
        "WebsiteURL": null,
        "ReputationPoints": 522,
        "Permissions": null,
        "PermissionsRequested": null,
        "DateCreated": null,
        "DateLastLogin": null,
        "IsProfilePublic": null,
        "IsEmergencyChargingProvider": null,
        "IsPublicChargingProvider": null,
        "Latitude": null,
        "Longitude": null,
        "EmailAddress": null,
        "EmailHash": null,
        "ProfileImageURL": "https://www.gravatar.com/avatar/7461f0dcedb3750bdc1cc7a5fae75362?s=80&d=robohash",
        "IsCurrentSessionTokenValid": null,
        "APIKey": null,
        "SyncedSettings": null
      },
      "DateCreated": {
        "$date": "2019-05-15T10:58:00Z"
      }
    },
    {
      "ID": 18390,
      "ChargePointID": 20922,
      "ItemURL": "https://s3-ap-southeast-2.amazonaws.com/openchargemap/images/GB/OCM20922/OCM-20922.orig.2019051510552083.jpg",
      "ItemThumbnailURL": "https://s3-ap-southeast-2.amazonaws.com/openchargemap/images/GB/OCM20922/OCM-20922.thmb.2019051510552083.jpg",
      "Comment": "",
      "IsEnabled": true,
      "IsVideo": false,
      "IsFeaturedItem": false,
      "IsExternalResource": false,
      "MetadataValue": null,
      "User": {
        "ID": 15366,
        "IdentityProvider": null,
        "Identifier": null,
        "CurrentSessionToken": null,
        "Username": "ZCWCara",
        "Profile": null,
        "Location": null,
        "WebsiteURL": null,
        "ReputationPoints": 522,
        "Permissions": null,
        "PermissionsRequested": null,
        "DateCreated": null,
        "DateLastLogin": null,
        "IsProfilePublic": null,
        "IsEmergencyChargingProvider": null,
        "IsPublicChargingProvider": null,
        "Latitude": null,
        "Longitude": null,
        "EmailAddress": null,
        "EmailHash": null,
        "ProfileImageURL": "https://www.gravatar.com/avatar/7461f0dcedb3750bdc1cc7a5fae75362?s=80&d=robohash",
        "IsCurrentSessionTokenValid": null,
        "APIKey": null,
        "SyncedSettings": null
      },
      "DateCreated": {
        "$date": "2019-05-15T10:56:00Z"
      }
    },
    {
      "ID": 18389,
      "ChargePointID": 20922,
      "ItemURL": "https://s3-ap-southeast-2.amazonaws.com/openchargemap/images/GB/OCM20922/OCM-20922.orig.2019051510534078.jpg",
      "ItemThumbnailURL": "https://s3-ap-southeast-2.amazonaws.com/openchargemap/images/GB/OCM20922/OCM-20922.thmb.2019051510534078.jpg",
      "Comment": "",
      "IsEnabled": true,
      "IsVideo": false,
      "IsFeaturedItem": false,
      "IsExternalResource": false,
      "MetadataValue": null,
      "User": {
        "ID": 15366,
        "IdentityProvider": null,
        "Identifier": null,
        "CurrentSessionToken": null,
        "Username": "ZCWCara",
        "Profile": null,
        "Location": null,
        "WebsiteURL": null,
        "ReputationPoints": 522,
        "Permissions": null,
        "PermissionsRequested": null,
        "DateCreated": null,
        "DateLastLogin": null,
        "IsProfilePublic": null,
        "IsEmergencyChargingProvider": null,
        "IsPublicChargingProvider": null,
        "Latitude": null,
        "Longitude": null,
        "EmailAddress": null,
        "EmailHash": null,
        "ProfileImageURL": "https://www.gravatar.com/avatar/7461f0dcedb3750bdc1cc7a5fae75362?s=80&d=robohash",
        "IsCurrentSessionTokenValid": null,
        "APIKey": null,
        "SyncedSettings": null
      },
      "DateCreated": {
        "$date": "2019-05-15T10:54:00Z"
      }
    }
  ],
  "LevelOfDetail": null,
  "Chargers": null,
  "MetadataTags": null,
  "SpatialPosition": {
    "type": "Point",
    "coordinates": [
      -4.242142,
      50.46006
    ]
  }
}
