{
  "ID": 24058,
  "UUID": "C8F5A88B-25FF-4A9E-AD12-E7350302CB7C",
  "ParentChargePointID": null,
  "DataProviderID": 1,
  "DataProvidersReference": null,
  "OperatorID": 1,
  "OperatorsReference": null,
  "UsageTypeID": 1,
  "UsageCost": "Free",
  "AddressInfo": {
    "ID": 24403,
    "Title": "Dolder Grand Hotel",
    "AddressLine1": "Kurhausstrasse 65",
    "AddressLine2": null,
    "Town": "Zurich",
    "StateOrProvince": "Zurich",
    "Postcode": "8032",
    "CountryID": 217,
    "Country": {
      "ID": 217,
      "Title": "Switzerland",
      "ISOCode": "CH",
      "ContinentCode": "EU"
    },
    "Latitude": 47.3729350883347,
    "Longitude": 8.57379182428279,
    "ContactTelephone1": null,
    "ContactTelephone2": null,
    "ContactEmail": null,
    "AccessComments": "Parking Level 2, Parking Fee: CHF 1/h",
    "RelatedURL": "http://www.thedoldergrand.com/",
    "Distance": null,
    "DistanceUnit": 0,
    "GeneralComments": null
  },
  "Connections": [
    {
      "ID": 26061,
      "ConnectionTypeID": 8,
      "ConnectionType": {
        "ID": 8,
        "Title": "Tesla (Roadster)",
        "FormalName": "Tesla Connector",
        "IsDiscontinued": true,
        "IsObsolete": false
      },
      "Reference": null,
      "StatusTypeID": 50,
      "StatusType": {
        "ID": 50,
        "Title": "Operational",
        "IsOperational": true,
        "IsUserSelectable": true
      },
      "LevelID": 2,
      "Level": {
        "ID": 2,
        "Title": "Level 2 : Medium (Over 2kW)",
        "Comments": "Over 2 kW, usually non-domestic socket type",
        "IsFastChargeCapable": false
      },
      "Amps": 63,
      "Voltage": 230,
      "PowerKW": 14.5,
      "CurrentTypeID": 10,
      "CurrentType": {
        "ID": 10,
        "Title": "AC (Single-Phase)",
        "Description": "Alternating Current - Single Phase"
      },
      "Quantity": 1,
      "Comments": null
    },
    {
      "ID": 26062,
      "ConnectionTypeID": 17,
      "ConnectionType": {
        "ID": 17,
        "Title": "CEE 5 Pin",
        "FormalName": null,
        "IsDiscontinued": false,
        "IsObsolete": false
      },
      "Reference": null,
      "StatusTypeID": 50,
      "StatusType": {
        "ID": 50,
        "Title": "Operational",
        "IsOperational": true,
        "IsUserSelectable": true
      },
      "LevelID": 2,
      "Level": {
        "ID": 2,
        "Title": "Level 2 : Medium (Over 2kW)",
        "Comments": "Over 2 kW, usually non-domestic socket type",
        "IsFastChargeCapable": false
      },
      "Amps": 32,
      "Voltage": 230,
      "PowerKW": 12.7,
      "CurrentTypeID": 20,
      "CurrentType": {
        "ID": 20,
        "Title": "AC (Three-Phase)",
        "Description": "Alternating Current - Three Phase"
      },
      "Quantity": 1,
      "Comments": null
    }
  ],
  "NumberOfPoints": 1,
  "GeneralComments": null,
  "DatePlanned": null,
  "DateLastConfirmed": null,
  "StatusTypeID": 50,
  "DateLastStatusUpdate": {
    "$date": "2014-06-12T20:37:00Z"
  },
  "MetadataValues": null,
  "DataQualityLevel": 1,
  "DateCreated": {
    "$date": "2014-06-09T23:02:00Z"
  },
  "SubmissionStatusTypeID": 200,
  "AddressCleaningRequired": false,
  "DataProvider": {
    "ID": 1,
    "Title": "Open Charge Map Contributors",
    "WebsiteURL": "http://openchargemap.org",
    "Comments": null,
    "DataProviderStatusType": {
      "ID": 1,
      "Title": "Manual Data Entry",
      "IsProviderEnabled": true
    },
    "IsRestrictedEdit": false,
    "IsOpenDataLicensed": true,
    "IsApprovedImport": true,
    "License": "Licensed under Creative Commons Attribution-ShareAlike 4.0 International (CC BY-SA 4.0)",
    "DateLastImported": null
  },
  "OperatorInfo": {
    "ID": 1,
    "Title": "(Unknown Operator)",
    "WebsiteURL": null,
    "Comments": null,
    "PhonePrimaryContact": null,
    "PhoneSecondaryContact": null,
    "IsPrivateIndividual": null,
    "AddressInfo": null,
    "BookingURL": null,
    "ContactEmail": null,
    "FaultReportEmail": null,
    "IsRestrictedEdit": null
  },
  "UsageType": {
    "ID": 1,
    "Title": "Public",
    "IsPayAtLocation": null,
    "IsMembershipRequired": null,
    "IsAccessKeyRequired": null
  },
  "StatusType": {
    "ID": 50,
    "Title": "Operational",
    "IsOperational": true,
    "IsUserSelectable": true
  },
  "SubmissionStatus": {
    "ID": 200,
    "Title": "Submission Published",
    "IsLive": true
  },
  "UserComments": null,
  "PercentageSimilarity": null,
  "MediaItems": null,
  "LevelOfDetail": null,
  "Chargers": null,
  "MetadataTags": null,
  "SpatialPosition": {
    "type": "Point",
    "coordinates": [
      8.57379182428279,
      47.3729350883347
    ]
  }
}
