{
  "ID": 31348,
  "UUID": "D4566DFC-F785-44C1-B312-A859105C9E28",
  "ParentChargePointID": null,
  "DataProviderID": 1,
  "DataProvidersReference": null,
  "OperatorID": 36,
  "OperatorsReference": null,
  "UsageTypeID": 1,
  "UsageCost": null,
  "AddressInfo": {
    "ID": 31694,
    "Title": "Knokkestraat - Elizabetlaan Knokke-Heist",
    "AddressLine1": "Knokkestraat",
    "AddressLine2": "Elizabetlaan",
    "Town": "Heist",
    "StateOrProvince": null,
    "Postcode": "8301",
    "CountryID": 26,
    "Country": {
      "ID": 26,
      "Title": "Belgium",
      "ISOCode": "BE",
      "ContinentCode": "EU"
    },
    "Latitude": 51.34008943172855,
    "Longitude": 3.241738449876377,
    "ContactTelephone1": null,
    "ContactTelephone2": null,
    "ContactEmail": null,
    "AccessComments": null,
    "RelatedURL": null,
    "Distance": null,
    "DistanceUnit": 0,
    "GeneralComments": null
  },
  "Connections": [
    {
      "ID": 34802,
      "ConnectionTypeID": 25,
      "ConnectionType": {
        "ID": 25,
        "Title": "Type 2 (Socket Only)",
        "FormalName": "IEC 62196-2 Type 2",
        "IsDiscontinued": false,
        "IsObsolete": false
      },
      "Reference": null,
      "StatusTypeID": 50,
      "StatusType": {
        "ID": 50,
        "Title": "Operational",
        "IsOperational": true,
        "IsUserSelectable": true
      },
      "LevelID": 2,
      "Level": {
        "ID": 2,
        "Title": "Level 2 : Medium (Over 2kW)",
        "Comments": "Over 2 kW, usually non-domestic socket type",
        "IsFastChargeCapable": false
      },
      "Amps": 32,
      "Voltage": 400,
      "PowerKW": 22,
      "CurrentTypeID": 20,
      "CurrentType": {
        "ID": 20,
        "Title": "AC (Three-Phase)",
        "Description": "Alternating Current - Three Phase"
      },
      "Quantity": 1,
      "Comments": null
    },
    {
      "ID": 34803,
      "ConnectionTypeID": 28,
      "ConnectionType": {
        "ID": 28,
        "Title": "CEE 7/4 - Schuko - Type F",
        "FormalName": "CEE 7/4",
        "IsDiscontinued": false,
        "IsObsolete": false
      },
      "Reference": null,
      "StatusTypeID": 50,
      "StatusType": {
        "ID": 50,
        "Title": "Operational",
        "IsOperational": true,
        "IsUserSelectable": true
      },
      "LevelID": 2,
      "Level": {
        "ID": 2,
        "Title": "Level 2 : Medium (Over 2kW)",
        "Comments": "Over 2 kW, usually non-domestic socket type",
        "IsFastChargeCapable": false
      },
      "Amps": 16,
      "Voltage": 230,
      "PowerKW": 3.7,
      "CurrentTypeID": 10,
      "CurrentType": {
        "ID": 10,
        "Title": "AC (Single-Phase)",
        "Description": "Alternating Current - Single Phase"
      },
      "Quantity": 1,
      "Comments": null
    }
  ],
  "NumberOfPoints": 2,
  "GeneralComments": null,
  "DatePlanned": null,
  "DateLastConfirmed": null,
  "StatusTypeID": 100,
  "DateLastStatusUpdate": {
    "$date": "2021-05-04T15:32:00Z"
  },
  "MetadataValues": null,
  "DataQualityLevel": 1,
  "DateCreated": {
    "$date": "2015-01-04T16:25:00Z"
  },
  "SubmissionStatusTypeID": 200,
  "AddressCleaningRequired": false,
  "DataProvider": {
    "ID": 1,
    "Title": "Open Charge Map Contributors",
    "WebsiteURL": "http://openchargemap.org",
    "Comments": null,
    "DataProviderStatusType": {
      "ID": 1,
      "Title": "Manual Data Entry",
      "IsProviderEnabled": true
    },
    "IsRestrictedEdit": false,
    "IsOpenDataLicensed": true,
    "IsApprovedImport": true,
    "License": "Licensed under Creative Commons Attribution-ShareAlike 4.0 International (CC BY-SA 4.0)",
    "DateLastImported": null
  },
  "OperatorInfo": {
    "ID": 36,
    "Title": "Blue Corner (Belgium)",
    "WebsiteURL": "http://www.bluecorner.be/",
    "Comments": null,
    "PhonePrimaryContact": null,
    "PhoneSecondaryContact": null,
    "IsPrivateIndividual": false,
    "AddressInfo": null,
    "BookingURL": null,
    "ContactEmail": null,
    "FaultReportEmail": null,
    "IsRestrictedEdit": null
  },
  "UsageType": {
    "ID": 1,
    "Title": "Public",
    "IsPayAtLocation": null,
    "IsMembershipRequired": null,
    "IsAccessKeyRequired": null
  },
  "StatusType": {
    "ID": 100,
    "Title": "Not Operational",
    "IsOperational": false,
    "IsUserSelectable": true
  },
  "SubmissionStatus": {
    "ID": 200,
    "Title": "Submission Published",
    "IsLive": true
  },
  "UserComments": [
    {
      "ID": 24283,
      "ChargePointID": 31348,
      "CommentTypeID": 50,
      "CommentType": {
        "ID": 50,
        "Title": "Important Notice (For Other Users)"
      },
      "UserName": "JRO",
      "Comment": "Charging Spot out of order",
      "Rating": null,
      "RelatedURL": null,
      "DateCreated": {
        "$date": "2021-05-04T00:09:03.313Z"
      },
      "User": {
        "ID": 31983,
        "IdentityProvider": null,
        "Identifier": null,
        "CurrentSessionToken": null,
        "Username": "JRO",
        "Profile": null,
        "Location": null,
        "WebsiteURL": null,
        "ReputationPoints": 5,
        "Permissions": null,
        "PermissionsRequested": null,
        "DateCreated": null,
        "DateLastLogin": null,
        "IsProfilePublic": null,
        "IsEmergencyChargingProvider": null,
        "IsPublicChargingProvider": null,
        "Latitude": null,
        "Longitude": null,
        "EmailAddress": null,
        "EmailHash": null,
        "ProfileImageURL": "https://www.gravatar.com/avatar/48722faba8d7a874b3238e11c42fc41b?s=80&d=robohash",
        "IsCurrentSessionTokenValid": null,
        "APIKey": null,
        "SyncedSettings": null
      },
      "CheckinStatusTypeID": 120,
      "CheckinStatusType": {
        "ID": 120,
        "Title": "Charging Spot Not Accessible (Access locked or site closed)",
        "IsPositive": false,
        "IsAutomatedCheckin": false
      },
      "IsActionedByEditor": false
    }
  ],
  "PercentageSimilarity": null,
  "MediaItems": [
    {
      "ID": 828,
      "ChargePointID": 31348,
      "ItemURL": "https://s3-ap-southeast-2.amazonaws.com/openchargemap/images/BE/OCM31348/OCM-31348.orig.2015010416245714.jpg",
      "ItemThumbnailURL": "https://s3-ap-southeast-2.amazonaws.com/openchargemap/images/BE/OCM31348/OCM-31348.thmb.2015010416245714.jpg",
      "Comment": "",
      "IsEnabled": true,
      "IsVideo": false,
      "IsFeaturedItem": false,
      "IsExternalResource": false,
      "MetadataValue": null,
      "User": {
        "ID": 1761,
        "IdentityProvider": null,
        "Identifier": null,
        "CurrentSessionToken": null,
        "Username": "filip.vanrickstal",
        "Profile": null,
        "Location": null,
        "WebsiteURL": null,
        "ReputationPoints": 169,
        "Permissions": null,
        "PermissionsRequested": null,
        "DateCreated": null,
        "DateLastLogin": null,
        "IsProfilePublic": null,
        "IsEmergencyChargingProvider": null,
        "IsPublicChargingProvider": null,
        "Latitude": null,
        "Longitude": null,
        "EmailAddress": null,
        "EmailHash": null,
        "ProfileImageURL": "https://www.gravatar.com/avatar/cc5c901d575be0479016ce4cc6a6f33e?s=80&d=robohash",
        "IsCurrentSessionTokenValid": null,
        "APIKey": null,
        "SyncedSettings": null
      },
      "DateCreated": {
        "$date": "2015-01-04T16:25:00Z"
      }
    },
    {
      "ID": 829,
      "ChargePointID": 31348,
      "ItemURL": "https://s3-ap-southeast-2.amazonaws.com/openchargemap/images/BE/OCM31348/OCM-31348.orig.2015010416251457.jpg",
      "ItemThumbnailURL": "https://s3-ap-southeast-2.amazonaws.com/openchargemap/images/BE/OCM31348/OCM-31348.thmb.2015010416251457.jpg",
      "Comment": "",
      "IsEnabled": true,
      "IsVideo": false,
      "IsFeaturedItem": false,
      "IsExternalResource": false,
      "MetadataValue": null,
      "User": {
        "ID": 1761,
        "IdentityProvider": null,
        "Identifier": null,
        "CurrentSessionToken": null,
        "Username": "filip.vanrickstal",
        "Profile": null,
        "Location": null,
        "WebsiteURL": null,
        "ReputationPoints": 169,
        "Permissions": null,
        "PermissionsRequested": null,
        "DateCreated": null,
        "DateLastLogin": null,
        "IsProfilePublic": null,
        "IsEmergencyChargingProvider": null,
        "IsPublicChargingProvider": null,
        "Latitude": null,
        "Longitude": null,
        "EmailAddress": null,
        "EmailHash": null,
        "ProfileImageURL": "https://www.gravatar.com/avatar/cc5c901d575be0479016ce4cc6a6f33e?s=80&d=robohash",
        "IsCurrentSessionTokenValid": null,
        "APIKey": null,
        "SyncedSettings": null
      },
      "DateCreated": {
        "$date": "2015-01-04T16:25:00Z"
      }
    }
  ],
  "LevelOfDetail": null,
  "Chargers": null,
  "MetadataTags": null,
  "SpatialPosition": {
    "type": "Point",
    "coordinates": [
      3.241738449876377,
      51.34008943172855
    ]
  }
}
