{
  "ID": 92081,
  "UUID": "F3A8FA7E-4C7C-4045-A3B1-43E692082EC0",
  "ParentChargePointID": null,
  "DataProviderID": 1,
  "DataProvidersReference": null,
  "OperatorID": 3,
  "OperatorsReference": "PG-91134,PG-91148,PG-91157",
  "UsageTypeID": 6,
  "UsageCost": "Free",
  "AddressInfo": {
    "ID": 92427,
    "Title": "Barras Car Centre-Hyundai",
    "AddressLine1": "Unit 3, Vale Garage Complex",
    "AddressLine2": "Route du Bray",
    "Town": "Vale",
    "StateOrProvince": null,
    "Postcode": "GY3 5PA",
    "CountryID": 96,
    "Country": {
      "ID": 96,
      "Title": "Guernsey",
      "ISOCode": "GG",
      "ContinentCode": "EU"
    },
    "Latitude": 49.485473,
    "Longitude": -2.521865,
    "ContactTelephone1": null,
    "ContactTelephone2": null,
    "ContactEmail": null,
    "AccessComments": null,
    "RelatedURL": null,
    "Distance": null,
    "DistanceUnit": 0,
    "GeneralComments": null
  },
  "Connections": [
    {
      "ID": 130554,
      "ConnectionTypeID": 25,
      "ConnectionType": {
        "ID": 25,
        "Title": "Type 2 (Socket Only)",
        "FormalName": "IEC 62196-2 Type 2",
        "IsDiscontinued": false,
        "IsObsolete": false
      },
      "Reference": null,
      "StatusTypeID": 50,
      "StatusType": {
        "ID": 50,
        "Title": "Operational",
        "IsOperational": true,
        "IsUserSelectable": true
      },
      "LevelID": 2,
      "Level": {
        "ID": 2,
        "Title": "Level 2 : Medium (Over 2kW)",
        "Comments": "Over 2 kW, usually non-domestic socket type",
        "IsFastChargeCapable": false
      },
      "Amps": 32,
      "Voltage": 230,
      "PowerKW": 7,
      "CurrentTypeID": 10,
      "CurrentType": {
        "ID": 10,
        "Title": "AC (Single-Phase)",
        "Description": "Alternating Current - Single Phase"
      },
      "Quantity": 3,
      "Comments": null
    }
  ],
  "NumberOfPoints": 3,
  "GeneralComments": "This is an open charge unit installed at the Barras Car Centre - Hyundai dealership in Vale Garage Complex, Route du Braye, Vale, Guernsey",
  "DatePlanned": null,
  "DateLastConfirmed": null,
  "StatusTypeID": 50,
  "DateLastStatusUpdate": {
    "$date": "2017-12-21T23:18:00Z"
  },
  "MetadataValues": null,
  "DataQualityLevel": 1,
  "DateCreated": {
    "$date": "2017-08-26T05:20:00Z"
  },
  "SubmissionStatusTypeID": 200,
  "AddressCleaningRequired": false,
  "DataProvider": {
    "ID": 1,
    "Title": "Open Charge Map Contributors",
    "WebsiteURL": "http://openchargemap.org",
    "Comments": null,
    "DataProviderStatusType": {
      "ID": 1,
      "Title": "Manual Data Entry",
      "IsProviderEnabled": true
    },
    "IsRestrictedEdit": false,
    "IsOpenDataLicensed": true,
    "IsApprovedImport": true,
    "License": "Licensed under Creative Commons Attribution-ShareAlike 4.0 International (CC BY-SA 4.0)",
    "DateLastImported": null
  },
  "OperatorInfo": {
    "ID": 3,
    "Title": "POD Point (UK)",
    "WebsiteURL": "http://www.pod-point.com/",
    "Comments": "Part of Groupe EDF",
    "PhonePrimaryContact": "020 7247 4114",
    "PhoneSecondaryContact": null,
    "IsPrivateIndividual": false,
    "AddressInfo": null,
    "BookingURL": null,
    "ContactEmail": "enquiries@pod-point.com",
    "FaultReportEmail": "enquiries@pod-point.com",
    "IsRestrictedEdit": false
  },
  "UsageType": {
    "ID": 6,
    "Title": "Private - For Staff, Visitors or Customers",
    "IsPayAtLocation": false,
    "IsMembershipRequired": false,
    "IsAccessKeyRequired": false
  },
  "StatusType": {
    "ID": 50,
    "Title": "Operational",
    "IsOperational": true,
    "IsUserSelectable": true
  },
  "SubmissionStatus": {
    "ID": 200,
    "Title": "Submission Published",
    "IsLive": true
  },
  "UserComments": null,
  "PercentageSimilarity": null,
  "MediaItems": null,
  "LevelOfDetail": null,
  "Chargers": null,
  "MetadataTags": null,
  "SpatialPosition": {
    "type": "Point",
    "coordinates": [
      -2.521865,
      49.485473
    ]
  }
}
