{
  "ID": 9271,
  "UUID": "B95B261A-619F-436B-911A-A3A56995FC14",
  "ParentChargePointID": null,
  "DataProviderID": 1,
  "DataProvidersReference": null,
  "OperatorID": 1,
  "OperatorsReference": null,
  "UsageTypeID": 1,
  "UsageCost": "Free",
  "AddressInfo": {
    "ID": 9168,
    "Title": "Eaton Canada",
    "AddressLine1": "5050 Mainway",
    "AddressLine2": "",
    "Town": "Burlington",
    "StateOrProvince": "Ontario",
    "Postcode": "L7L 5Z1",
    "CountryID": 44,
    "Country": {
      "ID": 44,
      "Title": "Canada",
      "ISOCode": "CA",
      "ContinentCode": "NA"
    },
    "Latitude": 43.3904271,
    "Longitude": -79.77767849999998,
    "ContactTelephone1": "",
    "ContactTelephone2": "",
    "ContactEmail": "",
    "AccessComments": "",
    "RelatedURL": "http://www.eatoncanada.ca/plugin",
    "Distance": null,
    "DistanceUnit": 0,
    "GeneralComments": null
  },
  "Connections": [
    {
      "ID": 6984,
      "ConnectionTypeID": 1,
      "ConnectionType": {
        "ID": 1,
        "Title": "Type 1 (J1772)",
        "FormalName": "SAE J1772-2009",
        "IsDiscontinued": null,
        "IsObsolete": null
      },
      "Reference": null,
      "StatusTypeID": 50,
      "StatusType": {
        "ID": 50,
        "Title": "Operational",
        "IsOperational": true,
        "IsUserSelectable": true
      },
      "LevelID": 2,
      "Level": {
        "ID": 2,
        "Title": "Level 2 : Medium (Over 2kW)",
        "Comments": "Over 2 kW, usually non-domestic socket type",
        "IsFastChargeCapable": false
      },
      "Amps": 30,
      "Voltage": 240,
      "PowerKW": 7.2,
      "CurrentTypeID": null,
      "CurrentType": null,
      "Quantity": 2,
      "Comments": null
    }
  ],
  "NumberOfPoints": 2,
  "GeneralComments": "",
  "DatePlanned": null,
  "DateLastConfirmed": null,
  "StatusTypeID": 50,
  "DateLastStatusUpdate": {
    "$date": "2012-02-01T14:12:00Z"
  },
  "MetadataValues": null,
  "DataQualityLevel": 1,
  "DateCreated": {
    "$date": "2012-01-30T21:38:00Z"
  },
  "SubmissionStatusTypeID": 200,
  "AddressCleaningRequired": false,
  "DataProvider": {
    "ID": 1,
    "Title": "Open Charge Map Contributors",
    "WebsiteURL": "http://openchargemap.org",
    "Comments": null,
    "DataProviderStatusType": {
      "ID": 1,
      "Title": "Manual Data Entry",
      "IsProviderEnabled": true
    },
    "IsRestrictedEdit": false,
    "IsOpenDataLicensed": true,
    "IsApprovedImport": true,
    "License": "Licensed under Creative Commons Attribution-ShareAlike 4.0 International (CC BY-SA 4.0)",
    "DateLastImported": null
  },
  "OperatorInfo": {
    "ID": 1,
    "Title": "(Unknown Operator)",
    "WebsiteURL": null,
    "Comments": null,
    "PhonePrimaryContact": null,
    "PhoneSecondaryContact": null,
    "IsPrivateIndividual": null,
    "AddressInfo": null,
    "BookingURL": null,
    "ContactEmail": null,
    "FaultReportEmail": null,
    "IsRestrictedEdit": null
  },
  "UsageType": {
    "ID": 1,
    "Title": "Public",
    "IsPayAtLocation": null,
    "IsMembershipRequired": null,
    "IsAccessKeyRequired": null
  },
  "StatusType": {
    "ID": 50,
    "Title": "Operational",
    "IsOperational": true,
    "IsUserSelectable": true
  },
  "SubmissionStatus": {
    "ID": 200,
    "Title": "Submission Published",
    "IsLive": true
  },
  "UserComments": null,
  "PercentageSimilarity": null,
  "MediaItems": null,
  "LevelOfDetail": null,
  "Chargers": null,
  "MetadataTags": null,
  "SpatialPosition": {
    "type": "Point",
    "coordinates": [
      -79.77767849999998,
      43.3904271
    ]
  }
}
